spacy_model_manager/__init__.py
spacy_model_manager/cli.py
spacy_model_manager/lib.py
spacy_model_manager-0.1.3.dist-info/AUTHORS
spacy_model_manager-0.1.3.dist-info/LICENSE
spacy_model_manager-0.1.3.dist-info/METADATA
spacy_model_manager-0.1.3.dist-info/WHEEL
spacy_model_manager-0.1.3.dist-info/entry_points.txt
spacy_model_manager-0.1.3.dist-info/top_level.txt
spacy_model_manager-0.1.3.dist-info/RECORD
