Metadata-Version: 2.1
Name: spacy-model-manager
Version: 0.1.3
Summary: Command line utility to view, install, and upgrade spaCy models
Home-page: https://github.com/carascap/spacy-model-manager
Author: CARASCAP
Author-email: carascap@protonmail.com
License: MIT
Platform: UNKNOWN
Classifier: Development Status :: 2 - Pre-Alpha
Requires-Python: >=3.7
License-File: LICENSE
